sycamore/README.md
sycamore/__init__.py
sycamore/connectors/aryn/ArynReader.py
sycamore/connectors/aryn/ArynWriter.py
sycamore/connectors/aryn/client.py
sycamore/connectors/base_reader.py
sycamore/connectors/base_writer.py
sycamore/connectors/common.py
sycamore/connectors/doc_reconstruct.py
sycamore/connectors/duckdb/__init__.py
sycamore/connectors/duckdb/duckdb_reader.py
sycamore/connectors/duckdb/duckdb_writer.py
sycamore/connectors/elasticsearch/__init__.py
sycamore/connectors/elasticsearch/elasticsearch_reader.py
sycamore/connectors/elasticsearch/elasticsearch_writer.py
sycamore/connectors/file/__init__.py
sycamore/connectors/file/file_scan.py
sycamore/connectors/file/file_writer.py
sycamore/connectors/file/file_writer_ray.py
sycamore/connectors/file/materialized_scan.py
sycamore/connectors/neo4j/__init__.py
sycamore/connectors/neo4j/neo4j_writer.py
sycamore/connectors/opensearch/__init__.py
sycamore/connectors/opensearch/opensearch_reader.py
sycamore/connectors/opensearch/opensearch_writer.py
sycamore/connectors/opensearch/sync.py
sycamore/connectors/opensearch/utils.py
sycamore/connectors/pinecone/__init__.py
sycamore/connectors/pinecone/pinecone_reader.py
sycamore/connectors/pinecone/pinecone_writer.py
sycamore/connectors/qdrant/__init__.py
sycamore/connectors/qdrant/qdrant_reader.py
sycamore/connectors/qdrant/qdrant_writer.py
sycamore/connectors/weaviate/__init__.py
sycamore/connectors/weaviate/weaviate_reader.py
sycamore/connectors/weaviate/weaviate_writer.py
sycamore/context.py
sycamore/data/__init__.py
sycamore/data/bbox.py
sycamore/data/docid.py
sycamore/data/document.py
sycamore/data/element.py
sycamore/data/metadata.py
sycamore/data/table.py
sycamore/decorators.py
sycamore/docset.py
sycamore/evaluation/__init__.py
sycamore/evaluation/data.py
sycamore/evaluation/datasets.py
sycamore/evaluation/evaluate.py
sycamore/evaluation/metrics/__init__.py
sycamore/evaluation/metrics/generated_answer.py
sycamore/evaluation/metrics/retrieval.py
sycamore_ai-0.1.33.dist-info/METADATA
sycamore_ai-0.1.33.dist-info/WHEEL
sycamore_ai-0.1.33.dist-info/RECORD
