Metadata-Version: 2.3
Name: sycamore-ai
Version: 0.1.33
Summary: Sycamore is an LLM-powered semantic data preparation system for building search applications.
Author: aryn.ai
Author-email: opensource@aryn.ai
Requires-Python: >=3.10,<3.14
Classifier: Programming Language :: Python :: 3
Classifier: Programming Language :: Python :: 3.10
Classifier: Programming Language :: Python :: 3.11
Classifier: Programming Language :: Python :: 3.12
Classifier: Programming Language :: Python :: 3.13
Provides-Extra: anthropic
Provides-Extra: docs
Provides-Extra: duckdb
Provides-Extra: elasticsearch
Provides-Extra: eval
Provides-Extra: google-genai
Provides-Extra: legacy-partitioners
Provides-Extra: local-inference
Provides-Extra: neo4j
Provides-Extra: opensearch
Provides-Extra: pinecone
Provides-Extra: qdrant
Provides-Extra: weaviate
Requires-Dist: aiohttp (>=3.12.14,<4.0.0)
Requires-Dist: amazon-textract-textractor (>=1.3.2,<2.0.0)
Requires-Dist: anthropic (>=0.42.0,<0.43.0) ; extra == "anthropic"
Requires-Dist: apted (>=1.0.3,<2.0.0) ; extra == "eval"
Requires-Dist: aryn-sdk (>=0.2.6)
Requires-Dist: async-timeout (>4.0.0)
Requires-Dist: beautifulsoup4 (>=4.13.1,<5.0.0)
Requires-Dist: boto3 (>=1.28.70,<2.0.0)
Requires-Dist: boto3-stubs[essential] (>=1.35.12,<2.0.0)
Requires-Dist: datasets (>=2.16.1,<3.0.0) ; extra == "eval"
Requires-Dist: dateparser (>=1.2.0,<2.0.0)
Requires-Dist: diskcache (>=5.6.3,<6.0.0)
Requires-Dist: duckdb (>=1.1.1,<2.0.0) ; extra == "duckdb"
Requires-Dist: easyocr (>=1.7.1,<2.0.0) ; extra == "local-inference"
Requires-Dist: elasticsearch (==8.14.0) ; extra == "elasticsearch"
Requires-Dist: fasteners (>=0.19,<0.20)
Requires-Dist: fsspec (==2024.2.0)
Requires-Dist: furo (>=2023.9.10,<2024.0.0) ; extra == "docs"
Requires-Dist: google-genai (>=1.14.0,<2.0.0) ; extra == "google-genai"
Requires-Dist: httpcore (>=1.0.9)
Requires-Dist: jinja2 (>=3.1.6,<4.0.0)
Requires-Dist: msgpack (>=1.1.1,<2.0.0)
Requires-Dist: myst-parser (>=2.0.0,<3.0.0) ; extra == "docs"
Requires-Dist: nanoid (>=2.0.0,<3.0.0)
Requires-Dist: neo4j (>=5.21.0,<6.0.0) ; extra == "neo4j"
Requires-Dist: nltk (>=3.9.0,<4.0.0) ; extra == "legacy-partitioners"
Requires-Dist: numpy (<2.0.0)
Requires-Dist: openai (>=1.60.2,<2.0.0)
Requires-Dist: opensearch-py (>=2.3.1,<3.0.0) ; extra == "opensearch"
Requires-Dist: overrides (>=7.7.0,<8.0.0)
Requires-Dist: paddleocr (>=3.1.0,<4.0.0) ; extra == "local-inference"
Requires-Dist: pandas (>=2.3.0,<3.0.0)
Requires-Dist: pdf2image (>=1.16.3,<2.0.0)
Requires-Dist: pdfminer-six (==20221105) ; extra == "local-inference"
Requires-Dist: pillow (>=11.3.0,<12.0.0)
Requires-Dist: pinecone-text (>=0.9.0,<0.10.0) ; extra == "pinecone"
Requires-Dist: pinecone[grpc] (>=6.0.2,<7.0.0) ; extra == "pinecone"
Requires-Dist: protobuf (>=5.29.5,<6.0.0)
Requires-Dist: pyarrow (>=20.0.0,<21.0.0)
Requires-Dist: pydantic (>=2.8.2,<3.0.0)
Requires-Dist: pypdf (>=5.1.0,<6.0.0)
Requires-Dist: pytesseract (>=0.3.10,<0.4.0) ; extra == "local-inference"
Requires-Dist: python-pptx (>=0.6.22,<0.7.0) ; extra == "legacy-partitioners"
Requires-Dist: qdrant-client (>=1.11.2,<2.0.0) ; extra == "qdrant"
Requires-Dist: ray[default] (>=2.46.0,<3.0.0)
Requires-Dist: rich (>=13.7.1,<14.0.0)
Requires-Dist: rouge (>=1.0.1,<2.0.0) ; extra == "eval"
Requires-Dist: sentence-transformers (>=3.0.1,<4.0.0) ; extra == "local-inference"
Requires-Dist: setuptools (>=78.1.1)
Requires-Dist: sphinx (>=7.2.5,<8.0.0) ; extra == "docs"
Requires-Dist: structlog (>=24.2.0,<25.0.0)
Requires-Dist: tenacity (>=8.4.1,<9.0.0)
Requires-Dist: tiktoken (>=0.8.0,<0.9.0)
Requires-Dist: timm (>=0.9.12,<0.10.0) ; extra == "local-inference"
Requires-Dist: torch (>=2.7.1,<3.0.0) ; extra == "local-inference"
Requires-Dist: torchvision (>=0.22.0,<0.23.0) ; extra == "local-inference"
Requires-Dist: tornado (>=6.5.0)
Requires-Dist: transformers (>=4.53.1,<5.0.0) ; extra == "local-inference"
Requires-Dist: typing-extensions (>=4.12.2,<5.0.0)
Requires-Dist: unstructured[pdf] (>=0.16.2,<0.17.0) ; extra == "legacy-partitioners"
Requires-Dist: urllib3 (>=2.5.0,<3)
Requires-Dist: weaviate-client (>=4.14.1) ; extra == "weaviate"
Project-URL: Documentation, https://sycamore.readthedocs.io
Project-URL: Repository, https://github.com/aryn-ai/sycamore.git
